nowledge_mem-1.1.0.dist-info/licenses/LICENSE
server/main.py
nowledge_mem-1.1.0.dist-info/METADATA
nowledge_mem-1.1.0.dist-info/WHEEL
nowledge_mem-1.1.0.dist-info/entry_points.txt
nowledge_mem-1.1.0.dist-info/top_level.txt
nowledge_mem-1.1.0.dist-info/RECORD
