Metadata-Version: 2.4
Name: nowledge-mem
Version: 1.1.0
Summary: A Python MCP server for Nowledge Mem
Author-email: "Nowledge Labs, LLC" <hello@nowledge-labs.ai>, Wey Gu <weyl.gu@gmail.com>
License: Apache-2.0
Classifier: License :: OSI Approved :: MIT License
Classifier: Programming Language :: Python :: 3
Classifier: Programming Language :: Python :: 3.13
License-File: LICENSE
Requires-Dist: fastmcp>=2.12.4
Dynamic: license-file
